gemeente_lwd1/__init__.py
gemeente_lwd1-0.1.dist-info/LICENSE.txt
gemeente_lwd1-0.1.dist-info/METADATA
gemeente_lwd1-0.1.dist-info/WHEEL
gemeente_lwd1-0.1.dist-info/top_level.txt
gemeente_lwd1-0.1.dist-info/RECORD
