Metadata-Version: 2.1
Name: gemeente-lwd1
Version: 0.1
Summary: Dit is een test voor een eigen package
Author: Hang Zheng
Author-email: hangzheng_1999@hotmail.com
Classifier: Programming Language :: Python :: 3
Classifier: License :: OSI Approved :: MIT License
Classifier: Operating System :: OS Independent
License-File: LICENSE.txt
